serff/__init__.py
serff/main.py
serff-0.0.1.dist-info/LICENSE
serff-0.0.1.dist-info/METADATA
serff-0.0.1.dist-info/WHEEL
serff-0.0.1.dist-info/top_level.txt
serff-0.0.1.dist-info/RECORD
