Metadata-Version: 2.1
Name: serff
Version: 0.0.1
Summary: A micro web server
Home-page: https://github.com/api-key-management-system/serff
Author: apinanyogaratnam
Author-email: apinanapinan@icloud.com
Classifier: Programming Language :: Python :: 3
Classifier: License :: OSI Approved :: MIT License
Classifier: Operating System :: OS Independent
Requires-Python: >=3.10.4
License-File: LICENSE
